adminlte/__init__.py
adminlte/admin.py
adminlte/apps.py
adminlte/config.py
adminlte/models.py
adminlte/tests.py
adminlte/views.py
adminlte/widgets.py
adminlte/static/admin/bootstrap/css/bootstrap.css
adminlte/static/admin/bootstrap/fonts/bootstrap/glyphicons-halflings-regular.eot
adminlte/static/admin/bootstrap/fonts/bootstrap/glyphicons-halflings-regular.svg
adminlte/static/admin/bootstrap/fonts/bootstrap/glyphicons-halflings-regular.ttf
adminlte/static/admin/bootstrap/fonts/bootstrap/glyphicons-halflings-regular.woff
adminlte/static/admin/bootstrap/fonts/bootstrap/glyphicons-halflings-regular.woff2
adminlte/static/admin/bootstrap/js/bootstrap.min.js
adminlte/static/admin/css/AdminLTE.min.css
adminlte/static/admin/css/site.css
adminlte/static/admin/css/skins/_all-skins.css
adminlte/static/admin/css/skins/_all-skins.min.css
adminlte/static/admin/css/skins/skin-black-light.css
adminlte/static/admin/css/skins/skin-black-light.min.css
adminlte/static/admin/css/skins/skin-black.css
adminlte/static/admin/css/skins/skin-black.min.css
adminlte/static/admin/css/skins/skin-blue-light.css
adminlte/static/admin/css/skins/skin-blue-light.min.css
adminlte/static/admin/css/skins/skin-blue.css
adminlte/static/admin/css/skins/skin-blue.min.css
adminlte/static/admin/css/skins/skin-green-light.css
adminlte/static/admin/css/skins/skin-green-light.min.css
adminlte/static/admin/css/skins/skin-green.css
adminlte/static/admin/css/skins/skin-green.min.css
adminlte/static/admin/css/skins/skin-purple-light.css
adminlte/static/admin/css/skins/skin-purple-light.min.css
adminlte/static/admin/css/skins/skin-purple.css
adminlte/static/admin/css/skins/skin-purple.min.css
adminlte/static/admin/css/skins/skin-red-light.css
adminlte/static/admin/css/skins/skin-red-light.min.css
adminlte/static/admin/css/skins/skin-red.css
adminlte/static/admin/css/skins/skin-red.min.css
adminlte/static/admin/css/skins/skin-yellow-light.css
django_lteadmin-0.3.0a0.dist-info/DESCRIPTION.rst
django_lteadmin-0.3.0a0.dist-info/METADATA
django_lteadmin-0.3.0a0.dist-info/RECORD
django_lteadmin-0.3.0a0.dist-info/WHEEL
django_lteadmin-0.3.0a0.dist-info/metadata.json
django_lteadmin-0.3.0a0.dist-info/top_level.txt
